[
  {
    "savol": "Lotin tili qaysi yevropa tillar oilasiga kiradi?",
    "A": "hind-evropa",
    "B": "rim",
    "C": "yunon",
    "D": "grek",
    "javob": "A"
  },
  {
    "savol": "Nima uchun unli harfning ustiga ikki nuqta qo`yiladi?",
    "A": "unlilar alohida-alohida o`qilishi uchun",
    "B": "bir tovushni berishi uchun",
    "C": "birga talaffuz qilinishi uchun",
    "D": "unlilar birga o`qilishi uchun",
    "javob": "A"
  },
  {
    "savol": "Lotin tilida urg`u so`zning qaysi bo`g`iniga tushmaydi?",
    "A": "oxiriga",
    "B": "umuman tushmaydi",
    "C": "2-bo`g`inga",
    "D": "3-bo`g`inga",
    "javob": "A"
  },
  {
    "savol": "Lotin alifbosida nechta harf bor?",
    "A": "25",
    "B": "20",
    "C": "22",
    "D": "23",
    "javob": "A"
  },
  {
    "savol": "Qaysi so`zda „ti” harf birikmasi [tsi] deb o`qiladi?",
    "A": "lectio",
    "B": "mixio",
    "C": "ostium",
    "D": "tibia",
    "javob": "A"
  },
  {
    "savol": "Qaysi so`zda „ti” harf birikmasi [tsi] deb o`qiladi?",
    "A": "articulatio",
    "B": "ostiuem",
    "C": "tibia",
    "D": "ossa",
    "javob": "A"
  },
  {
    "savol": "Qaysi so`zda “c” harfi [к] tovushini beradi?",
    "A": "cranium",
    "B": "cerebrum",
    "C": "cito",
    "D": "cingulum",
    "javob": "A"
  },
  {
    "savol": "“caput” so`zida“c” harfi qanday tovushni beradi?",
    "A": "[к]",
    "B": "[c]",
    "C": "[s]",
    "D": "[kv]",
    "javob": "A"
  },
  {
    "savol": "[kv] tovushini beradigan so`zni aniqlang",
    "A": "quadratus",
    "B": "cultus",
    "C": "cuticula",
    "D": "cutis",
    "javob": "A"
  },
  {
    "savol": "[ngu] tovushi qaysi so`zda “ngv” talaffuzini beradi?",
    "A": "sanguis",
    "B": "lingula",
    "C": "angulus",
    "D": "frangula",
    "javob": "A"
  },
  {
    "savol": "Lotin alifbosida nechta unli harf bor?",
    "A": "6",
    "B": "7",
    "C": "5",
    "D": "4",
    "javob": "A"
  },
  {
    "savol": "Y, y unli harfi qanday talaffuz qilinadi?",
    "A": "[i] unli tovushidek",
    "B": "[u] unli tovushidek",
    "C": "[e] unli tovushidek",
    "D": "[o] unli tovushidek",
    "javob": "A"
  },
  {
    "savol": "“constitutio” so`zida „ti” harf birikmasi qanday o`qiladi",
    "A": "[tsi]",
    "B": "[tiv]",
    "C": "[tia]",
    "D": "[tic]",
    "javob": "A"
  },
  {
    "savol": "Bir tovushni ifodalovchi ikki unli harf birikmasi nima deb ataladi?",
    "A": "diftong",
    "B": "digraf",
    "C": "monograf",
    "D": "monoftong",
    "javob": "A"
  },
  {
    "savol": "“K k” harfi qanday so`zlarda uchraydi?",
    "A": "faqatgina yunon va arab tilidan kirib kelgan atamalarda",
    "B": "faqatgina lotin va yunon tilidan kirib kelgan atamalarda",
    "C": "faqatgina arab tilidan kirib kelgan atamalarda",
    "D": "faqatgina lotin tilidan kirib kelgan atamalarda",
    "javob": "A"
  },
  {
    "savol": "“ph, th, ch, rh” quyidagilar nima?",
    "A": "digraf",
    "B": "diftong",
    "C": "birikma",
    "D": "monograf",
    "javob": "A"
  },
  {
    "savol": "Digraflarni toping?",
    "A": "ph, th, ch, rh",
    "B": "ch, au, rh, eu",
    "C": "ae, oe, au, eu",
    "D": "oe, ph, eu, th",
    "javob": "A"
  },
  {
    "savol": "Nega “Aёr”so`zida unli harfning ustiga ikki nuqta qo`yiladi?",
    "A": "ikki unli alohida-alohida o`qilishi uchun",
    "B": "birga talaffuz qilinishi uchun",
    "C": "unlilar birga o`qilishi uchun",
    "D": "bir tovushni berishi uchun",
    "javob": "A"
  },
  {
    "savol": "“C” harfi qaysi so`zda [k] deb o`qiladi",
    "A": "coccyx",
    "B": "cerebellum",
    "C": "coeruleus",
    "D": "cysto",
    "javob": "A"
  },
  {
    "savol": "Diftonglarni toping?",
    "A": "ae, oe, au, eu",
    "B": "ph, th, ch, rh",
    "C": "oe, ph, eu, th",
    "D": "ch, au, rh, eu",
    "javob": "A"
  },
  {
    "savol": "Diftong nima?",
    "A": "bir tovushni ifodalovchi ikki unli harf birikmasi",
    "B": "ikki tovushni ifodalochi ikki undosh harf birikmasi",
    "C": "ikki tovushni ifodalochi ikki unli harf birikmasi",
    "D": "bir tovushni ifodalochi ikki undosh harf birikmasi",
    "javob": "A"
  },
  {
    "savol": "Agar so`zning oxiridan ikkinchi bo`g`in cho`ziq bo`lsa,",
    "A": "urg`u o`sha bo`g`inning unli tovushiga tushadi",
    "B": "urg`u 3-bo`g`inga",
    "C": "urg`u umuman tushmaydi",
    "D": "urg`u tushadi",
    "javob": "A"
  },
  {
    "savol": "“ae, oe, au, eu” quyidagilar nima?",
    "A": "diftong",
    "B": "monograf",
    "C": "digraflar",
    "D": "birikma",
    "javob": "A"
  },
  {
    "savol": "“Ch” harf birikmasi deb talaffuz qilinadi",
    "A": "[x]",
    "B": "[f[",
    "C": "[ch]",
    "D": "[h]",
    "javob": "A"
  },
  {
    "savol": "“C” harfi qaysi so`zda [ts] deb o`qiladi",
    "A": "cytologia",
    "B": "corpuse",
    "C": "cauda",
    "D": "collum",
    "javob": "A"
  },
  {
    "savol": "“S” harfi ikki unli yoki har qanday bir unli bilan “m, n” undosh harflari o`rtasida qanday o`qiladi? “neoplasma”",
    "A": "[z]",
    "B": "[s]",
    "C": "[c]",
    "D": "[ts]",
    "javob": "A"
  },
  {
    "savol": "Digraf bu-",
    "A": "bitta tovush beradigan ikkita undosh harf birikmasi",
    "B": "bir tovushni ifodalochi ikki unli harf birikmasi",
    "C": "ikki tovushni ifodalochi ikki unli harf birikmasi",
    "D": "ikki tovushni ifodalochi ikki undosh harf birikmasi",
    "javob": "A"
  },
  {
    "savol": "Lotin alifbosida nechta digraph bor?",
    "A": "4",
    "B": "2",
    "C": "3",
    "D": "1",
    "javob": "A"
  },
  {
    "savol": "Qaysi so`zda „ti” [ti] harf birikmasi [tsi] deb o`qiladi",
    "A": "constitutio",
    "B": "mixtio",
    "C": "tibia",
    "D": "spatium",
    "javob": "A"
  },
  {
    "savol": "“ngu” harflar birikmasi unli oldida kelganda qanday o`qiladi?”lingua”",
    "A": "[ngv]",
    "B": "[ngua]",
    "C": "[nkv]",
    "D": "[nku]",
    "javob": "A"
  },
  {
    "savol": "Lotin alifbosida nechta diftong bor?",
    "A": "4",
    "B": "1",
    "C": "3",
    "D": "5",
    "javob": "A"
  },
  {
    "savol": "Ikki bo`g`inli so`zni toping",
    "A": "costa",
    "B": "vertebra",
    "C": "costalis",
    "D": "bacterium",
    "javob": "A"
  },
  {
    "savol": "Unli “br” birikmasi oldida kelsa, (ver-te-bra)",
    "A": "qisqa talaffuz etiladi",
    "B": "cho`ziqroq talaffuz etiladi",
    "C": "yarim cho`ziq talaffuz etiladi",
    "D": "yarim ochiq talaffuz etiladi",
    "javob": "A"
  },
  {
    "savol": "”ce - re - brum” da “br” birikmasi",
    "A": "qisqa talaffuz etiladi",
    "B": "cho`ziqroq talaffuz etiladi",
    "C": "yarim cho`ziq talaffuz etiladi",
    "D": "yarim ochiq talaffuz etiladi",
    "javob": "A"
  },
  {
    "savol": "Unli unlidan oldin kelsa “o - le - um” misolida",
    "A": "qisqa talaffuz etiladi",
    "B": "cho`ziqroq talaffuz etiladi",
    "C": "yarim cho`ziq talaffuz etiladi",
    "D": "yarim ochiq talaffuz etiladi",
    "javob": "A"
  },
  {
    "savol": "Agar bo`g`inda “ul , ol , ib , il , id” harf birikmalari bo`lsa,",
    "A": "qisqa talaffuz etiladi",
    "B": "cho`ziqroq talaffuz etiladi",
    "C": "yarim cho`ziq talaffuz etiladi",
    "D": "yarim ochiq talaffuz etiladi",
    "javob": "A"
  },
  {
    "savol": "“Dysenteria” , “ia” qo`shimchasiga ega bo`lgan yunon atamasida urg`u",
    "A": "i harfiga tushadi",
    "B": "ikkinchi bo`g`inga tushadi",
    "C": "uchinchi bo`g`inga tushadi",
    "D": "tushmaydi",
    "javob": "A"
  },
  {
    "savol": "Qachon bo`g`in cho`ziq talaffuz qilinadi?",
    "A": "agar bo`g`inda diftong bo`lsa: ae,oe",
    "B": "bo`g`inda “ul , ol , ib , il , id” harf birikmalari bo`lsa",
    "C": "bo`g`inda “ib , il , id” harf birikmalari bo`lsa",
    "D": "Unli “br” birikmasi oldida kelsa",
    "javob": "A"
  },
  {
    "savol": "Agar unli harf ikki va undan ortiq undosh harflar yoki “x” va “z” undoshlari oldida kelsa (maxīlla)",
    "A": "shu bo`g`in cho`ziq o`qiladi",
    "B": "qisqaroq talaffuz etiladi",
    "C": "yarim cho`ziq",
    "D": "yarim qisqaroq talaffuz etiladi",
    "javob": "A"
  },
  {
    "savol": "Moslashmagan aniqlovchili atamani aniqlang",
    "A": "basis cranii",
    "B": "fossa posterior",
    "C": "facies mandibularis",
    "D": "costa quinta",
    "javob": "A"
  },
  {
    "savol": "V turlanishdagi otni aniqlang",
    "A": "caries",
    "B": "angilus",
    "C": "crus, cruris",
    "D": "pubes",
    "javob": "A"
  },
  {
    "savol": "cavitas oris- atamasining tarjimasini aniqlang",
    "A": "og`iz bo`shlig`i",
    "B": "qorin bo`shlig`i",
    "C": "ko`krak bo`shlig`i",
    "D": "burun bo`shlig`i",
    "javob": "A"
  },
  {
    "savol": "Mushakning lug`at shaklini toping",
    "A": "musculus,i m",
    "B": "zygoma, is f",
    "C": "dens,dentis n",
    "D": "facies, is m",
    "javob": "A"
  },
  {
    "savol": "II turlanishdagi otni aniqlang",
    "A": "talus",
    "B": "plexus",
    "C": "hiatus",
    "D": "ductus",
    "javob": "A"
  },
  {
    "savol": "Gen. Sing shaklidagi otni aniqlang",
    "A": "cranii",
    "B": "ala",
    "C": "digitus",
    "D": "costa",
    "javob": "A"
  },
  {
    "savol": "IV turlanishdagi otni aniqlang.",
    "A": "textus",
    "B": "nervus",
    "C": "musculus",
    "D": "radius",
    "javob": "A"
  },
  {
    "savol": "V turlanishdagi ot qaysi variantda berilgan",
    "A": "facies",
    "B": "pes",
    "C": "pubes",
    "D": "stapes",
    "javob": "A"
  },
  {
    "savol": "Moslashmagan aniqlovchili atamani aniqlang",
    "A": "apex linguae",
    "B": "musculus anterior",
    "C": "musculus longus",
    "D": "ren dexter",
    "javob": "A"
  },
  {
    "savol": "Gen. Sing shaklidagi otni aniqlang",
    "A": "venae",
    "B": "vena",
    "C": "apex",
    "D": "sternum",
    "javob": "A"
  },
  {
    "savol": "Qaysi javobda otning lug`at shakli to`gri ko`rsatilgan",
    "A": "costa, ae f",
    "B": "liber, bra, brum",
    "C": "scapula, i f",
    "D": "septum, us f",
    "javob": "A"
  },
  {
    "savol": "II turlanishdagi otni toping",
    "A": "nasus",
    "B": "ductus",
    "C": "processus",
    "D": "tractus",
    "javob": "A"
  },
  {
    "savol": "Moslashmagan aniqlovchili atamani aniqlang",
    "A": "meatus nasi",
    "B": "columna vertebralis",
    "C": "paries lateralis",
    "D": "os occipitale",
    "javob": "A"
  },
  {
    "savol": "Moslashmagan aniqlovchili atamani aniqlang",
    "A": "spina scapulae",
    "B": "os occipitale",
    "C": "caput longum",
    "D": "paries lateralis",
    "javob": "A"
  },
  {
    "savol": "Moslashmagan aniqlovchili atamani aniqlang",
    "A": "vestibulum nasi",
    "B": "palatum molle",
    "C": "palatum durum",
    "D": "concha nasalis",
    "javob": "A"
  },
  {
    "savol": "Lug`at shakli to`g`ri yozilgan otni toping",
    "A": "oculus i m",
    "B": "sternum, i m",
    "C": "recessus, i n",
    "D": "textus, i f",
    "javob": "A"
  },
  {
    "savol": "Qaratqich kelishik lotinchada nima?",
    "A": "genetivus",
    "B": "nominativus",
    "C": "dativus",
    "D": "accusativus",
    "javob": "A"
  },
  {
    "savol": "II turlanish sredniy rodning Nominativusdagi qo`shimchasi?",
    "A": "-um",
    "B": "-us",
    "C": "-a",
    "D": "-im",
    "javob": "A"
  },
  {
    "savol": "V turlanishdagi otni toping",
    "A": "caries, ei f",
    "B": "truncus, i n",
    "C": "paries, etis m",
    "D": "pes, pedis m",
    "javob": "A"
  },
  {
    "savol": "Moslashmagan aniqlovchili atamani aniqlang.",
    "A": "corpus maxillae",
    "B": "glandula alveolaris",
    "C": "ligamentum teres",
    "D": "ductus major",
    "javob": "A"
  },
  {
    "savol": "Lotin tilida sifatlar nimaga moslashadi?",
    "A": "rodda, sonda va kelishikda",
    "B": "kelishikda",
    "C": "sonda",
    "D": "rodda",
    "javob": "A"
  },
  {
    "savol": "I guruh sifatlari nechta qo`shimchaga ega?",
    "A": "3 ta",
    "B": "2 va 1ta",
    "C": "1ta",
    "D": "2ta",
    "javob": "A"
  },
  {
    "savol": "II guruh sifatlari nechta qo`shimchaga ega?",
    "A": "3-2-1ta",
    "B": "1ta",
    "C": "2ta",
    "D": "3ta",
    "javob": "A"
  },
  {
    "savol": "I guruh sifat qo`shimchalari qaysilar?",
    "A": "us, er (m); a (f); um (n);",
    "B": "is (m,f); e (n)",
    "C": "e (n)",
    "D": "is (m,f);",
    "javob": "A"
  },
  {
    "savol": "II guruh sifat qo`shimchalari qaysilar?",
    "A": "is (m,f); e (n)",
    "B": "us, er (m);",
    "C": "us,on (m);",
    "D": "er ,um (m);",
    "javob": "A"
  },
  {
    "savol": "Bir qo`shimchali sifatni toping",
    "A": "teres",
    "B": "ala",
    "C": "digitus",
    "D": "costa",
    "javob": "A"
  },
  {
    "savol": "Qaysilar II guruh sifatlari?",
    "A": "costalis,e",
    "B": "sinister, tra, trum",
    "C": "liber, era, erum",
    "D": "albus",
    "javob": "A"
  },
  {
    "savol": "II guruh sifatni toping",
    "A": "nasalis, e",
    "B": "altus,a,um",
    "C": "liber, era, erum",
    "D": "albus",
    "javob": "A"
  },
  {
    "savol": "I guruh sifatni toping",
    "A": "latus,a,um",
    "B": "simplex",
    "C": "costalis,e",
    "D": "nasalis, e",
    "javob": "A"
  },
  {
    "savol": "dexter, tra, trum tarjimasi nima?",
    "A": "o`ng",
    "B": "chap",
    "C": "orqa",
    "D": "past",
    "javob": "A"
  },
  {
    "savol": "ruber, bra, brum tarjimasi nima?",
    "A": "qizil",
    "B": "sariq",
    "C": "oq",
    "D": "qora",
    "javob": "A"
  },
  {
    "savol": "qisqa mushak -tarjimasi",
    "A": "musculus brevis",
    "B": "musculus dextrus",
    "C": "musculus niger",
    "D": "musculus alba",
    "javob": "A"
  },
  {
    "savol": "sternalis ,e- tarjimasi",
    "A": "to`shga oid",
    "B": "tishga oid",
    "C": "qovurg`aga oid",
    "D": "mushakka oid",
    "javob": "A"
  },
  {
    "savol": "dentalis,e- tarjimasi",
    "A": "tishga oid",
    "B": "umurtqaga oid",
    "C": "qovurg`ga oid",
    "D": "suyakka oid",
    "javob": "A"
  },
  {
    "savol": "“ponasimon suyak” ning tarjimasi",
    "A": "os sphenoidale",
    "B": "os occipitale",
    "C": "caput longum",
    "D": "paries lateralis",
    "javob": "A"
  },
  {
    "savol": "Lug`at shakli to`g`ri yozilgan sifatni toping",
    "A": "sinister, tra, trum",
    "B": "dextera,us,a",
    "C": "rectus,a,e",
    "D": "transversum,a,ur",
    "javob": "A"
  },
  {
    "savol": "“qoziq tish” tarjimasi",
    "A": "dens caninus",
    "B": "dens molares",
    "C": "dens premolaris",
    "D": "dens serotinus",
    "javob": "A"
  },
  {
    "savol": "“katta oziq tish” tarjimasi",
    "A": "dens molaris",
    "B": "dens premolaris",
    "C": "dens serotinis",
    "D": "dens canina",
    "javob": "A"
  },
  {
    "savol": "“vena profunda” ning ma`nosini toping",
    "A": "chuqur vena",
    "B": "uzun vena",
    "C": "kalta vena",
    "D": "o`ng vena",
    "javob": "A"
  },
  {
    "savol": "“Uzun suyak” ning ma`nosini toping",
    "A": "os longum",
    "B": "os costa",
    "C": "os brevis",
    "D": "ossis",
    "javob": "A"
  },
  {
    "savol": "Sifatni moslashtiring “Orqa yuza”",
    "A": "facies posterior",
    "B": "facies articularis",
    "C": "facies jugularis",
    "D": "facies temporalis",
    "javob": "A"
  },
  {
    "savol": "To`gri moslashgan aniqlovchili atamani toping",
    "A": "labium superius",
    "B": "tuberculum pharyngea",
    "C": "linea ruber",
    "D": "musculus longum",
    "javob": "A"
  },
  {
    "savol": "Moslashtiring: katta teshik",
    "A": "foramen magnum",
    "B": "foramen jugularis",
    "C": "foramen ovalis",
    "D": "foramen rotundus",
    "javob": "A"
  },
  {
    "savol": "Birinchi guruh sifatni aniqlang",
    "A": "laryngeus,a,um",
    "B": "parietalis,e",
    "C": "occipital,e",
    "D": "ethmoidalis,e",
    "javob": "A"
  },
  {
    "savol": "Birinchi guruh sifatni aniqlang",
    "A": "rectus,a,um",
    "B": "frontalis,e",
    "C": "lacrimalis,e",
    "D": "orbitalis,e",
    "javob": "A"
  },
  {
    "savol": "Birinchi guruh sifatni aniqlang",
    "A": "zygomaticus,a,um",
    "B": "nasalis,e",
    "C": "temporalis,e",
    "D": "sphenoidalis,e",
    "javob": "A"
  },
  {
    "savol": "“ Dens incisivus primus (centralis)” atamasini tarjima qiling",
    "A": "birinchi (asosiy) kurak tish",
    "B": "ikkinchi (lateral)kurak tish",
    "C": "qoziq tish",
    "D": "kichik oziq (premolyar) tish",
    "javob": "A"
  },
  {
    "savol": "“egri chiziq” tarjimasi-",
    "A": "linea obliquua",
    "B": "linea rectus",
    "C": "linea transversum",
    "D": "linea asper",
    "javob": "A"
  },
  {
    "savol": "“ichki qiyshiq qorin mushagi” tarjimasi-",
    "A": "muskulus obliquus internus abdominis",
    "B": "muskulus obliquus externus abdominis",
    "C": "muskulus rectus externus abdominis",
    "D": "muskulus latus externus abdominis",
    "javob": "A"
  },
  {
    "savol": "To`gri moslashgan aniqlovchili atamani toping",
    "A": "musculus latissimus dorsi",
    "B": "linea gluteus major",
    "C": "vena laryngeum externus",
    "D": "arteria renale",
    "javob": "A"
  },
  {
    "savol": "“Yashil rang” ning yunonchasi-",
    "A": "chloro",
    "B": "polio",
    "C": "leuco",
    "D": "xantho",
    "javob": "A"
  },
  {
    "savol": "“Qizil rang” ning yunonchasi-",
    "A": "erythro",
    "B": "leuco",
    "C": "melano",
    "D": "cyano",
    "javob": "A"
  },
  {
    "savol": "Suyak nomini ayting: “g`alvirsimon suyak”",
    "A": "os ethmoidale",
    "B": "os lacrimale",
    "C": "os nasale",
    "D": "os frontale",
    "javob": "A"
  },
  {
    "savol": "“incisura ischiadica major` atamasini tarjima qiling",
    "A": "katta quymich o`yig`i",
    "B": "pastrki to`gri chiziq",
    "C": "oldingi bo`ylama boylam",
    "D": "kichik quymich do`mboqchasi",
    "javob": "A"
  },
  {
    "savol": "“incisura vertebralis”- nima deyiladi?",
    "A": "umurtqa o`ymasi",
    "B": "umutrqa yoyi",
    "C": "umurtqa suyagi",
    "D": "umurtqa",
    "javob": "A"
  },
  {
    "savol": "“vertebra cervicalis” ning tarjimasi",
    "A": "bo`yin umurtqasi",
    "B": "bel umurtqasi",
    "C": "ko`krak umurtqasi",
    "D": "dum umurtqasi",
    "javob": "A"
  },
  {
    "savol": "Birinchi guruh sifatni aniqlang.",
    "A": "xyphoideus",
    "B": "sulcus",
    "C": "plexus",
    "D": "meatus",
    "javob": "A"
  },
  {
    "savol": "Moslashtiring: o`ng yelka",
    "A": "brachium dextrum",
    "B": "clavicula sinistra",
    "C": "arteria dextra",
    "D": "vena sinistra",
    "javob": "A"
  },
  {
    "savol": "Suyak nomini ayting: “tanglay suyagi”",
    "A": "os palatinum",
    "B": "os occipitale",
    "C": "os parietale",
    "D": "os nasale",
    "javob": "A"
  },
  {
    "savol": "To`gri moslashgan aniqlovchili atamani toping",
    "A": "palatum molle",
    "B": "musculus pharyngea",
    "C": "oculus nigra",
    "D": "nervus petrosum",
    "javob": "A"
  },
  {
    "savol": "“Sutura nasomaxillaris”- tarjimasini toping",
    "A": "burun-yuqori jag` choki",
    "B": "yonoq-yuqori jag` choki",
    "C": "peshona-yonoq suyagi choki",
    "D": "ponasimon- peshona suyak choki",
    "javob": "A"
  },
  {
    "savol": "Ikkinchi guruh sifatini aniqlang",
    "A": "distalis",
    "B": "ruber",
    "C": "dextra",
    "D": "altus",
    "javob": "A"
  },
  {
    "savol": "Tarjima qiling: qanotsimon o`siq",
    "A": "processus pterygoideus",
    "B": "processus mastoideus",
    "C": "processus styloideus",
    "D": "processus mammilaris",
    "javob": "A"
  },
  {
    "savol": "IV turlanish genus neutrum (sredniy rod)dagi otni toping",
    "A": "genu",
    "B": "genus",
    "C": "gustus",
    "D": "glomus",
    "javob": "A"
  },
  {
    "savol": "III turlanish genus neutrum (sredniy rod)dagi otni toping",
    "A": "diaphragma",
    "B": "lingua",
    "C": "linea",
    "D": "sutura",
    "javob": "A"
  },
  {
    "savol": "“plicae tunicae mucosae nasi” atamasini tarjima qiling",
    "A": "burun shilliq qavatining burmalari",
    "B": "og`iz shilliq qavatining burmalari",
    "C": "tanglay shilliq qavatining burmalari",
    "D": "kekirdak shilliq qavatining burmalari",
    "javob": "A"
  },
  {
    "savol": "“nucleus nervi hypoglossi” atamasini tarjima qiling",
    "A": "tilosti nervining yadrosi",
    "B": "og`iz nervining yadrosi",
    "C": "tanglay nervining yadrosi",
    "D": "burun nervining yadrosi",
    "javob": "A"
  },
  {
    "savol": "“sulcus venae cavae” atamasini tarjima qiling",
    "A": "kovak vena egati",
    "B": "burun egati",
    "C": "jag` egati",
    "D": "to`g`ri vena egati",
    "javob": "A"
  },
  {
    "savol": "“rima oris” -atamasining tarjimasini toping",
    "A": "og`iz yorig`i",
    "B": "og`iz bo`shlig`i",
    "C": "og`iz burmasi",
    "D": "og`iz dahlizi",
    "javob": "A"
  },
  {
    "savol": "“basis crania externa” atamasining tarjimasini toping",
    "A": "kallaning tashqi asosi",
    "B": "kallaning ichki asos",
    "C": "kallaning yuqori asos",
    "D": "kallaning orqa asos",
    "javob": "A"
  },
  {
    "savol": "“processus articularis superior” atamasining tarjimasini toping",
    "A": "yuqori bo`g`im o`sig`i",
    "B": "pastki bo`g`im o`sig`i",
    "C": "ichki bo`g`im o`sig`i",
    "D": "tashqi bo`g`im o`sig`i",
    "javob": "A"
  },
  {
    "savol": "IV turlanishdagi otni aniqlang",
    "A": "hiatus, us m",
    "B": "corpus,oris n",
    "C": "organismus, i, m",
    "D": "sulcus, i m",
    "javob": "A"
  },
  {
    "savol": "“arcus palatoglossus” atamasining tarjimasini toping",
    "A": "tanglaytil yoyi",
    "B": "tanglaytil arteriyasi",
    "C": "tanglaytil mushagi",
    "D": "tanglaytil oqimi",
    "javob": "A"
  },
  {
    "savol": "III turlanish sredniy roddagi otni toping",
    "A": "pectus",
    "B": "lobus",
    "C": "tractus",
    "D": "thymus",
    "javob": "A"
  },
  {
    "savol": "“sulcus nervi petrosi”atamasining tarjimasini toping",
    "A": "toshsimon nerv egati",
    "B": "burun egati",
    "C": "qovurg`a yoyi",
    "D": "o`mrov yoyi",
    "javob": "A"
  },
  {
    "savol": "“vena cerebri interna”atamasining tarjimasini toping",
    "A": "miyaning ichki venasi",
    "B": "miyaning tashqi venasi",
    "C": "miyaning oldingi venasi",
    "D": "miyaning pastgi venasi",
    "javob": "A"
  },
  {
    "savol": "“dumg`aza kanali”atamasining tarjimasini toping",
    "A": "canalis sacralis",
    "B": "canalis nervi",
    "C": "canalis palatinum",
    "D": "canalis",
    "javob": "A"
  },
  {
    "savol": "“pastki jag` o`yig`i” atamasining tarjimasini toping",
    "A": "incisura mandibulae",
    "B": "incisura ischiadica minor",
    "C": "incisura acetabuli",
    "D": "incisura scapulae",
    "javob": "A"
  },
  {
    "savol": "Agar so`zda nechta unli harf bo`lsa",
    "A": "shuncha bo`g`in bo`ladi",
    "B": "shuncha undosh harf bo`ladi",
    "C": "shuncha bo`ladi",
    "D": "shuncha undosh bo`ladi",
    "javob": "A"
  },
  {
    "savol": "“dumg`aza kanalining pastki teshigi” atamasining tarjimasini toping",
    "A": "foramen posterius canalis sacralis",
    "B": "foramen posterius",
    "C": "canalis sacralis",
    "D": "foramen magnum canalis musculus",
    "javob": "A"
  },
  {
    "savol": "“th” harf birikmasi qanday talaffuz qilinadi",
    "A": "[t]",
    "B": "[z]",
    "C": "[c]",
    "D": "[h]",
    "javob": "A"
  },
  {
    "savol": "“bo`yin umurtqalari” atamasining tarjimasini toping",
    "A": "vertebrae cervicales",
    "B": "vertebrae thoracicae",
    "C": "vertebrae lumbalis",
    "D": "vertebrae dorsalis",
    "javob": "A"
  },
  {
    "savol": "“to`shning dastasi”atamasining tarjimasini toping",
    "A": "manubrium sterni",
    "B": "cavitas medullaris",
    "C": "rima oris",
    "D": "cavitas oris",
    "javob": "A"
  },
  {
    "savol": "Lotin alifbosida nechta undosh harf bor?",
    "A": "19",
    "B": "15",
    "C": "12",
    "D": "16",
    "javob": "A"
  },
  {
    "savol": "“sutura frontozygomatica” atamasining tarjimasini toping",
    "A": "peshanayonoq choki",
    "B": "peshana choki",
    "C": "yonoq choki",
    "D": "peshanateppa choki",
    "javob": "A"
  },
  {
    "savol": "“sutura sphenofrontalis” atamasining tarjimasini toping",
    "A": "ponasimon peshana choki",
    "B": "g`alvirsimon chok",
    "C": "peshanateppa chok",
    "D": "yonoq chok",
    "javob": "A"
  },
  {
    "savol": "Unli qisqa talaffuz qilinadi",
    "A": "Agar unli harf bl, br, cl , cr, di, dr, pl, tl, tr harf birikmalari oldida kelsa",
    "B": "Agar bo`g`inda ur, in, at, ut qo`shimchalari bo`lsa",
    "C": "Agar bo`g`inda ar, al, os qo`shimchalari bo`lsa",
    "D": "Agar bo`g`inda ae, oe, eu qo`shimchalari bo`lsa",
    "javob": "A"
  },
  {
    "savol": "“Tog`aylar” atamasining to`g`ri tarjimasini toping",
    "A": "cartilagines",
    "B": "tendines",
    "C": "pulmones",
    "D": "pollices",
    "javob": "A"
  },
  {
    "savol": "“Lab bezlari” atamasining to`g`ri tarjimasini toping",
    "A": "glandulae labiales",
    "B": "glandulae salivariae",
    "C": "glandulae orales",
    "D": "glandulae uterinae",
    "javob": "A"
  },
  {
    "savol": "“Ligg.” atamasi qaysi atamaning qisqartma shakli",
    "A": "boylamlar",
    "B": "bo`g`imlar",
    "C": "belbog`lar",
    "D": "birikmalar",
    "javob": "A"
  },
  {
    "savol": "“aa. nutriciae” ning tarjimasi",
    "A": "oziqlantiruvchi arteriyalar",
    "B": "buyrak arteriyalari",
    "C": "yurak arteriyalari",
    "D": "tashuvchi arteriyalar",
    "javob": "A"
  },
  {
    "savol": "V turlanish otlarining Nom.Pl qo`shimchasini toping",
    "A": "-es",
    "B": "-u",
    "C": "-ae",
    "D": "-um",
    "javob": "A"
  },
  {
    "savol": "Gen.Pl otlarining II turlanishdagi qo`shimchasini toping",
    "A": "-orum",
    "B": "-arum",
    "C": "-uum",
    "D": "-erum",
    "javob": "A"
  },
  {
    "savol": "“Fonticuli cranii” atamasining to`g`ri tarjimasini toping",
    "A": "kallaning liqildoqlari",
    "B": "kallaning choklari",
    "C": "kallaning suyaklari",
    "D": "kallaning chiziqlari",
    "javob": "A"
  },
  {
    "savol": "Oddiy daraja qanday nomlanadi?",
    "A": "positivus",
    "B": "comparativus",
    "C": "superlativus",
    "D": "conjunctivus",
    "javob": "A"
  },
  {
    "savol": "Qiyosiy daraja qanday nomlanadi?",
    "A": "comparativus",
    "B": "genus",
    "C": "masculinum",
    "D": "femininum",
    "javob": "A"
  },
  {
    "savol": "Orttirma daraja qanday nomlanadi?",
    "A": "superlativus",
    "B": "positivus",
    "C": "neutrum",
    "D": "nominativus",
    "javob": "A"
  },
  {
    "savol": "I turlanishdagi otni toping",
    "A": "sutura",
    "B": "diafragma",
    "C": "stroma",
    "D": "systema",
    "javob": "A"
  },
  {
    "savol": "V turlanishdagi otni toping",
    "A": "rabies, ei f",
    "B": "truncus, i n",
    "C": "paries, etis m",
    "D": "pes, pedis m",
    "javob": "A"
  },
  {
    "savol": "IV turlanishdagi otni toping",
    "A": "manus",
    "B": "oculus",
    "C": "neonatus",
    "D": "nasus",
    "javob": "A"
  },
  {
    "savol": "Unli tovush qachon qisqa o`qiladi? Char-ta",
    "A": "Agar unli harf ch, th, ph, rh harf birikmalari oldida kelsa",
    "B": "Agar unli harf ngu, ti, su harf birikmalari oldida kelsa",
    "C": "Agar unli harf tt, ss, eu harf birikmalari oldida kelsa",
    "D": "Agar unli harf ae, oe, au harf birikmalari oldida kelsa",
    "javob": "A"
  },
  {
    "savol": "“pnoё” so`zida unli harfning ustiga ikki nuqta qo`yilish sababi nima?",
    "A": "alohida talaffuz qilinishi uchun",
    "B": "bir tovushni berishi uchun",
    "C": "birga talaffuz qilinishi uchun",
    "D": "birga o`qilishi uchun",
    "javob": "A"
  },
  {
    "savol": "Murakkab sifatlar qaysi unli bilan birlashadi",
    "A": "-o-",
    "B": "-i-",
    "C": "-a-",
    "D": "-e-",
    "javob": "A"
  },
  {
    "savol": "“therapia” atamasida urg`u qaysi unliga tushadi?",
    "A": "urg`u i harfiga tushadi",
    "B": "urg`u e harfiga tushadi",
    "C": "urg`u a harfiga tushadi",
    "D": "urg`u o harfiga tushadi",
    "javob": "A"
  },
  {
    "savol": "Qachon bo`g`in cho`ziq o`qiladi?",
    "A": "Agar bo`g`inda at,al,ar, in ot yasovchi qo`shimcha bo`lsa",
    "B": "Agar bo`g`inda bl, br ot yasovchi qo`shimcha bo`lsa",
    "C": "Agar bo`g`inda ul, il ot yasovchi qo`shimcha bo`lsa",
    "D": "Agar bo`g`inda ch, th ot yasovchi qo`shimcha bo`lsa",
    "javob": "A"
  },
  {
    "savol": "Til nima?",
    "A": "lingua-glosso",
    "B": "osteo-os",
    "C": "myo-musculus",
    "D": "hydro-aqua",
    "javob": "A"
  },
  {
    "savol": "“aneamia” atamasida urg`u qaysi unliga tushadi?",
    "A": "urg`u i harfiga tushadi",
    "B": "urg`u e harfiga tushadi",
    "C": "urg`u a harfiga tushadi",
    "D": "urg`u o harfiga tushadi",
    "javob": "A"
  },
  {
    "savol": "Qon bosimining ko`tarilishi-",
    "A": "hypertonia",
    "B": "hypotonia",
    "C": "dystonia",
    "D": "atonia",
    "javob": "A"
  },
  {
    "savol": "“Ph” harf birikmasi qanday talaffuz qilinadi",
    "A": "[f]",
    "B": "[p]",
    "C": "[x]",
    "D": "[h]",
    "javob": "A"
  },
  {
    "savol": "“C” harfi qaysi so`zda [ts] deb o`qiladi",
    "A": "cyto",
    "B": "corpus",
    "C": "cranium",
    "D": "cum",
    "javob": "A"
  },
  {
    "savol": "III turlanish mujskoy roddagi “ko`mir” otni toping",
    "A": "carbo, onis",
    "B": "tabes, is",
    "C": "articulatio, onis",
    "D": "femur, oris",
    "javob": "A"
  },
  {
    "savol": "“Tuz” ning lotincha nomlanishi?",
    "A": "sal",
    "B": "gingiva",
    "C": "solutio",
    "D": "sanum",
    "javob": "A"
  },
  {
    "savol": "“mel” ning o`zbekcha nomlanishi?",
    "A": "asal",
    "B": "tuz",
    "C": "un",
    "D": "tosh",
    "javob": "A"
  },
  {
    "savol": "“septum” ning o`zbekcha nomlanishi?",
    "A": "to`siq",
    "B": "yoy",
    "C": "o`yma",
    "D": "burchak",
    "javob": "A"
  },
  {
    "savol": "“Funksiyaning buzilishi” old qo`shimchasi qaysi",
    "A": "dys",
    "B": "a, an",
    "C": "hyper",
    "D": "hypo",
    "javob": "A"
  },
  {
    "savol": "Tishni oziqlantiruvchi qavatning nomi nima?",
    "A": "pulpa",
    "B": "dentinum",
    "C": "eminentium",
    "D": "periostium",
    "javob": "A"
  },
  {
    "savol": "Shakarning lotincha nomlanishi?",
    "A": "saccharum",
    "B": "sanus",
    "C": "sal",
    "D": "solutio",
    "javob": "A"
  },
  {
    "savol": "“Yuqori jag`” ning lotincha-yunoncha dubleti?",
    "A": "maxilla-gnatho",
    "B": "mandibula-genio",
    "C": "rhino-nasus",
    "D": "auris-oto",
    "javob": "A"
  },
  {
    "savol": "milkning lotincha nomi nima?",
    "A": "gingiva",
    "B": "dens",
    "C": "oris",
    "D": "aurum",
    "javob": "A"
  },
  {
    "savol": "tanglayning lotincha nomi nima?",
    "A": "palatum",
    "B": "larynx",
    "C": "pharynx",
    "D": "molli",
    "javob": "A"
  },
  {
    "savol": "Qaysi javobda limfa tuguni atamasi to`gri berilgan",
    "A": "nodus lymphaticum",
    "B": "vas sanguineum",
    "C": "vasorum",
    "D": "vas capillare",
    "javob": "A"
  },
  {
    "savol": "Oddiy daraja sifatini toping",
    "A": "magnus, a, um",
    "B": "longissimus, a, um",
    "C": "maximus, a, um",
    "D": "anterior, ius",
    "javob": "A"
  },
  {
    "savol": "Uchinchi molyar (aql tishi)-bu",
    "A": "dens molaris tertius",
    "B": "dens incisivus",
    "C": "dens premolaris",
    "D": "dens caninus",
    "javob": "A"
  },
  {
    "savol": "Index- nima?",
    "A": "ko`rsatkich barmoq",
    "B": "jimjiloq",
    "C": "o`rta barmoq",
    "D": "nomsiz barmoq",
    "javob": "A"
  },
  {
    "savol": "«xanjarsimon o`siq» atamasi qaysi javobda to`g`ri berilgan",
    "A": "processus xyphoideus",
    "B": "processus mastoideus",
    "C": "processus transversus",
    "D": "processus ethmoideus",
    "javob": "A"
  },
  {
    "savol": "“Igna bilan davolash” iborasini toping",
    "A": "acupunctura",
    "B": "hormonotherapia",
    "C": "physiologiya",
    "D": "heliotherapia",
    "javob": "A"
  },
  {
    "savol": "Gen. Sing shaklidagi otni aniqlang",
    "A": "nodi",
    "B": "musculus",
    "C": "apex",
    "D": "tuberculum",
    "javob": "A"
  },
  {
    "savol": "“Til osti nervi» iborasini toping",
    "A": "nervus hypoglossus",
    "B": "nervus vagus",
    "C": "nervus subcutaneus",
    "D": "nervus trigeminus",
    "javob": "A"
  },
  {
    "savol": "“Tabiiy davolash” iborasini toping",
    "A": "physiotherapia",
    "B": "hormonotherapia",
    "C": "therapia",
    "D": "heliotherapia",
    "javob": "A"
  },
  {
    "savol": "„Davolash” ma`nosini bildiradigan atamani yunoncha – lotincha dubletini aniqlang?",
    "A": "therapia – curatio",
    "B": "neuro – nervus",
    "C": "angio – vas, vasis",
    "D": "toxo–venenum",
    "javob": "A"
  },
  {
    "savol": "Systema urinarium –",
    "A": "siydik chiqarish tizimi",
    "B": "chakka suyagi",
    "C": "chakka o`yig`i",
    "D": "nerv tizimi",
    "javob": "A"
  },
  {
    "savol": "Systema cardiovasculare –",
    "A": "yurak-qon tomir tizimi",
    "B": "yelka tanasi",
    "C": "uzun bosh",
    "D": "nafas olish tizimi",
    "javob": "A"
  },
  {
    "savol": "Tishning 80 % ni tashkil etuvchi, qattiq to`qimasining nomi-",
    "A": "dentinum",
    "B": "enamelum",
    "C": "vas",
    "D": "gingiva",
    "javob": "A"
  },
  {
    "savol": "Na`matak lotinchada nomlanishi?",
    "A": "Rosa",
    "B": "Mentha",
    "C": "Chamomilla",
    "D": "Valeriana",
    "javob": "A"
  },
  {
    "savol": "Qaysi so`zda “c” harfi [ts] tovushini beradi.",
    "A": "celulla",
    "B": "columna",
    "C": "caput",
    "D": "capsula",
    "javob": "A"
  },
  {
    "savol": "Tishning ildiz qismini qoplovchi qavat-bu",
    "A": "cementum",
    "B": "pulpa",
    "C": "dentinum",
    "D": "enamelum",
    "javob": "A"
  },
  {
    "savol": "Hujayralarni o`rganuvchi fan-",
    "A": "cytologia",
    "B": "haematologia",
    "C": "odontologia",
    "D": "embryologia",
    "javob": "A"
  },
  {
    "savol": "Tishni o`rganuvchi fan-",
    "A": "odontologia",
    "B": "cardiologiya",
    "C": "haematologia",
    "D": "dermatologiya",
    "javob": "A"
  },
  {
    "savol": "Oqiz bo`shlig`i kasalliklarini o`rganuvchi fan-",
    "A": "stomotologiya",
    "B": "miologiya",
    "C": "haematologia",
    "D": "revmotologiya",
    "javob": "A"
  },
  {
    "savol": "“pollex” so`zining ma`nosini toping",
    "A": "bosh barmoq",
    "B": "ko`rsatkich barmoq",
    "C": "o`rta barmoq",
    "D": "jimjiloq",
    "javob": "A"
  },
  {
    "savol": "„Og`iz bo`shlig`ining yallig`lanishi” ma`nosini beradigan atamani toping",
    "A": "stomatitis",
    "B": "gingivitis",
    "C": "glossitis",
    "D": "arthritis",
    "javob": "A"
  },
  {
    "savol": "“Tuber frontale” so`zining ma`nosi",
    "A": "peshona do`mbog`i",
    "B": "peshona suyagi",
    "C": "peshona cheti",
    "D": "peshona yuzasi",
    "javob": "A"
  },
  {
    "savol": "„Katta” atamasining yunonchada nomlanishini toping",
    "A": "macro",
    "B": "micro",
    "C": "erythro",
    "D": "melano",
    "javob": "A"
  },
  {
    "savol": "„Og`riq” so`zini lotincha – yunoncha dubletini toping",
    "A": "dolor – algia",
    "B": "pulmo-pneumo",
    "C": "haemo – sanguis",
    "D": "dens-odonto",
    "javob": "A"
  },
  {
    "savol": "Tuberculum dentis-bu",
    "A": "tish bo`rtiqchasi",
    "B": "tish ildizi",
    "C": "tish yuzasi",
    "D": "tish bo`yinchasi",
    "javob": "A"
  },
  {
    "savol": "Tishning gumbazi-bu",
    "A": "fornix dentis",
    "B": "radix dentis",
    "C": "pulpa dentis",
    "D": "canalis dentis",
    "javob": "A"
  },
  {
    "savol": "Deltasimon mushak-",
    "A": "musculus deltoideus",
    "B": "musculus colli",
    "C": "musculus abdominis",
    "D": "musculus carpi",
    "javob": "A"
  },
  {
    "savol": "Mujskoy rodning lotincha variantini tanlang",
    "A": "genus masculinum",
    "B": "femininum",
    "C": "genetivus",
    "D": "genus nominativum",
    "javob": "A"
  },
  {
    "savol": "tishning pulpa bo`shlig`i",
    "A": "cavitas pulpae",
    "B": "cavitas radix",
    "C": "crista marginalis",
    "D": "radix palatinalis",
    "javob": "A"
  },
  {
    "savol": "Jenskiy rodning lotincha variantini tanlang",
    "A": "genus femininum",
    "B": "genus masculinum",
    "C": "genus neutrum",
    "D": "genus genetivum",
    "javob": "A"
  },
  {
    "savol": "Milkning yallig`lanishi- bu",
    "A": "gingivitis",
    "B": "pharyngitis",
    "C": "laryngitis",
    "D": "tracheitis",
    "javob": "A"
  },
  {
    "savol": "Qaysi so`zda bo`g`in qisqa talaffuz qilinadi?",
    "A": "vertebra",
    "B": "unguentum",
    "C": "reflexus",
    "D": "aquosus",
    "javob": "A"
  },
  {
    "savol": "V turlanishdagi otni aniqlang",
    "A": "species",
    "B": "stapes",
    "C": "crus, cruris",
    "D": "pubes",
    "javob": "A"
  },
  {
    "savol": "Tovushning cho`ziqligini belgilash uchun harf ustiga",
    "A": "to`g`ri chiziqcha",
    "B": "yoysimon chiziqcha",
    "C": "egri chiziqcha",
    "D": "aylana chiziqcha",
    "javob": "A"
  },
  {
    "savol": "II turlanishdagi otni aniqlang",
    "A": "sulcus,i",
    "B": "arcus,us",
    "C": "tempus,oris",
    "D": "textus,us",
    "javob": "A"
  },
  {
    "savol": "III turlanish sredniy roddagi otni toping",
    "A": "corpus,oris",
    "B": "musculus,i",
    "C": "meatus,us",
    "D": "sulcus,i",
    "javob": "A"
  },
  {
    "savol": "“abdomen” so`zini Gen. Sing (qaratqich kelishigi) qo`shimchasini toping",
    "A": "-inis",
    "B": "-icis",
    "C": "-is",
    "D": "-oris",
    "javob": "A"
  },
  {
    "savol": "“cartilago” so`zini Gen. Sing (qaratqich kelishigi) qo`shimchasini toping",
    "A": "-inis",
    "B": "-eris",
    "C": "-itis",
    "D": "-oris",
    "javob": "A"
  },
  {
    "savol": "“gaster” so`zini Gen. Sing (qaratqich kelishigi) qo`shimchasini toping",
    "A": "-tris",
    "B": "-idis",
    "C": "-is",
    "D": "-eris",
    "javob": "A"
  },
  {
    "savol": "“Musculus serratus anterior” tarjimasi",
    "A": "oldingi tishsimon muskul",
    "B": "orqa narvonsimon muskul",
    "C": "yuqori kamabalasimon muskul",
    "D": "pastki deltasimon muskul",
    "javob": "A"
  },
  {
    "savol": "“corpus” so`zini Gen. Sing (qaratqich kelishigi) qo`shimchasini toping",
    "A": "-oris",
    "B": "-inis",
    "C": "-is",
    "D": "-eris",
    "javob": "A"
  },
  {
    "savol": "“tendo” so`zini Gen. Sing (qaratqich kelishigi) qo`shimchasini toping",
    "A": "-inis",
    "B": "-icis",
    "C": "-idis",
    "D": "-tris",
    "javob": "A"
  },
  {
    "savol": "“femur” so`zini Gen. Sing (qaratqich kelishigi) qo`shimchasini toping",
    "A": "-oris",
    "B": "-itis",
    "C": "-edis",
    "D": "-onis",
    "javob": "A"
  },
  {
    "savol": "Moslashgan aniqlovchili atamani toping",
    "A": "costa vera",
    "B": "arcus vertebrae",
    "C": "caput fibulae",
    "D": "os pubis",
    "javob": "A"
  },
  {
    "savol": "“homo” so`zini Gen. Sing (qaratqich kelishigi) qo`shimchasini toping",
    "A": "-inis",
    "B": "-itis",
    "C": "-idis",
    "D": "-onis",
    "javob": "A"
  },
  {
    "savol": "Qiyosiy darajada to`g`ri yozilgan sifatni aniqlang",
    "A": "minor, us",
    "B": "sinister, tra, trum",
    "C": "magnus, um",
    "D": "rectus, um, a",
    "javob": "A"
  },
  {
    "savol": "“tog`ay” so`zini Nom. Pl (bosh kelishik ko`pligini) toping",
    "A": "cartilagines",
    "B": "vertebrae",
    "C": "ulnae",
    "D": "radii",
    "javob": "A"
  },
  {
    "savol": "“tugun” so`zini Nom. Pl (bosh kelishik ko`pligini) toping",
    "A": "nodi",
    "B": "ulnae",
    "C": "sulci",
    "D": "lineae",
    "javob": "A"
  },
  {
    "savol": "“bo`lak” so`zini Nom. Pl (bosh kelishik ko`pligini) toping",
    "A": "lobi",
    "B": "lingulae",
    "C": "foramina",
    "D": "fissurae",
    "javob": "A"
  },
  {
    "savol": "qiyosiy daraja sifatini toping",
    "A": "major,jus",
    "B": "rectus",
    "C": "mastoideus",
    "D": "latus",
    "javob": "A"
  },
  {
    "savol": "“tizza” so`zini Nom. Pl (bosh kelishik ko`pligini) toping",
    "A": "genua",
    "B": "foveae",
    "C": "dentes",
    "D": "labiae",
    "javob": "A"
  },
  {
    "savol": "“yuza” so`zini Nom. Pl (bosh kelishik ko`pligini) toping",
    "A": "facies",
    "B": "incisurae",
    "C": "dentium",
    "D": "cementum",
    "javob": "A"
  },
  {
    "savol": "“teshik” so`zini Nom. Pl (bosh kelishik ko`pligini) toping",
    "A": "foramina",
    "B": "septi",
    "C": "cranii",
    "D": "cerebri",
    "javob": "A"
  },
  {
    "savol": "qiyosiy daraja sifatini toping",
    "A": "minor,us",
    "B": "longus",
    "C": "latus",
    "D": "caecum",
    "javob": "A"
  },
  {
    "savol": "“tish” so`zini Nom. Pl (bosh kelishik ko`pligini) toping",
    "A": "dentes",
    "B": "canales",
    "C": "lobi",
    "D": "nasi",
    "javob": "A"
  },
  {
    "savol": "“boylam” so`zini Nom. Pl (bosh kelishik ko`pligini) toping",
    "A": "ligamenta",
    "B": "bursae",
    "C": "genua",
    "D": "cornu",
    "javob": "A"
  },
  {
    "savol": "“o`yma” so`zini Nom. Pl (bosh kelishik ko`pligini) toping",
    "A": "incisurae",
    "B": "fascies",
    "C": "nodus",
    "D": "vertebrae",
    "javob": "A"
  },
  {
    "savol": "“to`siq” so`zini Nom. Pl (bosh kelishik ko`pligini) toping",
    "A": "septa",
    "B": "lamina",
    "C": "sutura",
    "D": "ulna",
    "javob": "A"
  },
  {
    "savol": "Sutura coronalis-",
    "A": "tojsimon chok",
    "B": "ponasimon chok",
    "C": "g`alvirsimon chok",
    "D": "peshana choki",
    "javob": "A"
  },
  {
    "savol": "Sutura squamosa-",
    "A": "palla choki",
    "B": "yanoq choki",
    "C": "tojsimon chok",
    "D": "ponasimon chok",
    "javob": "A"
  },
  {
    "savol": "Processus styloideus-",
    "A": "bigizsimon o`siq",
    "B": "Orqa miya",
    "C": "pastki jag` tanasi",
    "D": "o`siq",
    "javob": "A"
  },
  {
    "savol": "orttirma daraja sifatini toping",
    "A": "optimus, a, um",
    "B": "longus, a, um",
    "C": "magnus, a, um",
    "D": "anterior, ius",
    "javob": "A"
  },
  {
    "savol": "Arcus zygomaticus-",
    "A": "yanoq yoyi",
    "B": "o`sma",
    "C": "yuqori jag` tanasi",
    "D": "ko`r teshik",
    "javob": "A"
  },
  {
    "savol": "Corpus mandibulae-",
    "A": "pastki jag` tanasi",
    "B": "qovurg`a tanasi",
    "C": "umurtqa tanasi",
    "D": "teshik",
    "javob": "A"
  },
  {
    "savol": "Corpus maxillae-",
    "A": "yuqori jag` tanasi",
    "B": "yelka tanasi",
    "C": "uzun bosh",
    "D": "qisqa mushak",
    "javob": "A"
  },
  {
    "savol": "Fossa temporalis-",
    "A": "chakka chuqurchasi",
    "B": "chakka suyagi",
    "C": "chakka o`yig`i",
    "D": "chakka",
    "javob": "A"
  },
  {
    "savol": "orttirma daraja sifatini toping",
    "A": "pessimus, a, um",
    "B": "albus, a, um",
    "C": "lactus, a, um",
    "D": "posterior, ius",
    "javob": "A"
  },
  {
    "savol": "Spina nasalis anterior-",
    "A": "burunning oldingi qirrasi",
    "B": "burunning yuqori chig`anog`i",
    "C": "burunning pastki qirrasi",
    "D": "burunning orga chig`anog`i",
    "javob": "A"
  },
  {
    "savol": "burunning yuqori chig`anog`i —",
    "A": "concha nasalis superior",
    "B": "os hyoideum",
    "C": "spina nasalis anterior",
    "D": "vestibulum nasi",
    "javob": "A"
  },
  {
    "savol": "kekirdak tog`aylari —",
    "A": "cartilagines laryngis",
    "B": "cornu majus ossis hyoidei",
    "C": "pars squamosa",
    "D": "nodi dexter",
    "javob": "A"
  },
  {
    "savol": "burun-halqum yo`li —",
    "A": "meatus nasopharyngeus",
    "B": "corona dentis",
    "C": "radix dentis",
    "D": "collum dentis",
    "javob": "A"
  },
  {
    "savol": "burun dahlizi —",
    "A": "vestibulum nasi",
    "B": "costa vera",
    "C": "arcus vertebrae",
    "D": "caput fibulae",
    "javob": "A"
  },
  {
    "savol": "lambdasimon chok chok",
    "A": "sutura lambdoidea",
    "B": "arteriae ciliares",
    "C": "arteria carotica",
    "D": "nodi lymphatici anteriores",
    "javob": "A"
  },
  {
    "savol": "til osti suyagi —",
    "A": "os hyoideum",
    "B": "nodi lymphatici anteriores",
    "C": "spina nasalis",
    "D": "musculus abdominis",
    "javob": "A"
  },
  {
    "savol": "til osti suyagining katta shoxi —",
    "A": "cornu majus ossis hyoidei",
    "B": "musculus abdominis",
    "C": "arteriae ciliares",
    "D": "arteria carotica",
    "javob": "A"
  },
  {
    "savol": "qiyosiy daraja sifatini toping",
    "A": "albior,ius",
    "B": "albus,a,um",
    "C": "albussimus",
    "D": "alba",
    "javob": "A"
  },
  {
    "savol": "Sutura frontozygomatica",
    "A": "peshanayanoq choki",
    "B": "tojsimon chok",
    "C": "to`g`ri chok",
    "D": "ipsimon chok",
    "javob": "A"
  },
  {
    "savol": "Systema skeletale –",
    "A": "tayanch harakat tizimi",
    "B": "tana tizimi",
    "C": "nafas olish tizimi",
    "D": "yurak tizimi",
    "javob": "A"
  },
  {
    "savol": "Systema musculare-",
    "A": "mushak tizimi",
    "B": "sezgi tizimi",
    "C": "siydik chiqarish tizimi",
    "D": "ayiruv tizimi",
    "javob": "A"
  },
  {
    "savol": "Systema endocrinum-",
    "A": "endokrin tizim",
    "B": "immun tizimi",
    "C": "katta teshik",
    "D": "kichik teshik",
    "javob": "A"
  },
  {
    "savol": "Systema nervosum –",
    "A": "nerv tizimi",
    "B": "mushak tizimi",
    "C": "iyak teshigi",
    "D": "qon tomir",
    "javob": "A"
  },
  {
    "savol": "Systema digestorium –",
    "A": "ovqat hazm qilish tizimi",
    "B": "chakka suyagi",
    "C": "ta`m bilish",
    "D": "siydik chiqarish tizimi",
    "javob": "A"
  },
  {
    "savol": "Foramen ovale-",
    "A": "oval teshik",
    "B": "qisqa teshik",
    "C": "yirtiq teshik",
    "D": "ko`r teshik",
    "javob": "A"
  },
  {
    "savol": "Foramen caecum -",
    "A": "ko`r teshik",
    "B": "katta teshik",
    "C": "oval teshik",
    "D": "qisqa teshik",
    "javob": "A"
  },
  {
    "savol": "Foramen lymphaticum-",
    "A": "limfa teshigi",
    "B": "iyak teshigi",
    "C": "ensa teshigi",
    "D": "katta teshik",
    "javob": "A"
  },
  {
    "savol": "“Bo`gim yuzasi” tarjimasini toping",
    "A": "facies articularis",
    "B": "facies temporalis",
    "C": "facies frontalis",
    "D": "facies ethmoidalis",
    "javob": "A"
  },
  {
    "savol": "Atamaning mos tarjimasini toping: “yuzaki limfa tuguni”",
    "A": "nodus lymphaticus superfacialis",
    "B": "nodus lymphatici posterior",
    "C": "nodi lymphatici anteriores",
    "D": "nodus lymphatici inferioris",
    "javob": "A"
  },
  {
    "savol": "orttirma daraja sifatini toping",
    "A": "maximus, a, um",
    "B": "longus, a, um",
    "C": "magnus, a, um",
    "D": "anterior, ius",
    "javob": "A"
  }
]